tmdbapi/__init__.py
tmdbapi/_core.py
tmdbapi/creds.py
tmdbapi/exceptions.py
tmdbapi/api3/__init__.py
tmdbapi/api3/_params_info_v3.py
tmdbapi/api3/account.py
tmdbapi/api3/authentication.py
tmdbapi/api3/certifications.py
tmdbapi/api3/changes.py
tmdbapi/api3/collections.py
tmdbapi/api3/companies.py
tmdbapi/api3/configuration.py
tmdbapi/api3/credits.py
tmdbapi/api3/discover.py
tmdbapi/api3/find.py
tmdbapi/api3/genres.py
tmdbapi/api3/guest_sessions.py
tmdbapi/api3/keywords.py
tmdbapi/api3/lists.py
tmdbapi/api3/movie_lists.py
tmdbapi/api3/movies.py
tmdbapi/api3/networks.py
tmdbapi/api3/people.py
tmdbapi/api3/reviews.py
tmdbapi/api3/search.py
tmdbapi/api3/trending.py
tmdbapi/api3/tv_episode_groups.py
tmdbapi/api3/tv_episodes.py
tmdbapi/api3/tv_seasons.py
tmdbapi/api3/tv_series.py
tmdbapi/api3/tv_series_lists.py
tmdbapi/api3/watch_providers.py
tmdbapi/api4/__init__.py
tmdbapi/api4/_params_info_v4.py
tmdbapi/api4/account.py
tmdbapi/api4/auth.py
tmdbapi/api4/lists.py
tmdbapi/integration/__init__.py
tmdbapi/integration/auth.py
tmdbapi/tests/__init__.py
tmdbapi/tests/conftest.py
tmdbapi/tests/test_tmdbapi.py
tmdbapi/tests/api3/__init__.py
tmdbapi/tests/api3/test_account.py
tmdbapi/tests/api3/test_authentication.py
tmdbapi/tests/api3/test_certifications.py
tmdbapi/tests/api3/test_changes.py
tmdbapi/tests/api3/test_collections.py
tmdbapi/tests/api3/test_companies.py
tmdbapi/tests/api3/test_configuration.py
tmdbapi/tests/api3/test_credits.py
tmdbapi/tests/api3/test_discover.py
tmdbapi/tests/api3/test_find.py
tmdbapi/tests/api3/test_genres.py
tmdbapi/tests/api3/test_guest_sessions.py
tmdbapi/tests/api3/test_keywords.py
tmdbapi/tests/api3/test_lists.py
tmdbapi/tests/api3/test_movie_lists.py
tmdbapi/tests/api3/test_movies.py
tmdbapi/tests/api3/test_networks.py
tmdbapi/tests/api3/test_people.py
tmdbapi/tests/api3/test_reviews.py
tmdbapi/tests/api3/test_search.py
tmdbapi/tests/api3/test_trending.py
tmdbapi/tests/api3/test_tv_episode_groups.py
tmdbapi/tests/api3/test_tv_episodes.py
TMDB_Py-1.1.1.dist-info/LICENSE
TMDB_Py-1.1.1.dist-info/METADATA
TMDB_Py-1.1.1.dist-info/WHEEL
TMDB_Py-1.1.1.dist-info/top_level.txt
TMDB_Py-1.1.1.dist-info/RECORD
