Metadata-Version: 2.1
Name: TMDB-Py
Version: 1.1.1
Summary: TheMovieDB (TMDB) API Python Request Library
Author-email: Patrick Liu <32678320+patrick-csliu@users.noreply.github.com>
Maintainer-email: Patrick Liu <32678320+patrick-csliu@users.noreply.github.com>
License: MIT License
Project-URL: Homepage, https://github.com/patrick-csliu/TMDB-API-Python
Project-URL: Bug Tracker, https://github.com/patrick-csliu/TMDB-API-Python/issues
Project-URL: Repository, https://github.com/patrick-csliu/TMDB-API-Python.git
Classifier: Programming Language :: Python :: 3
Classifier: Topic :: Internet
Classifier: Operating System :: OS Independent
Classifier: License :: OSI Approved :: MIT License
Requires-Python: >=3.11
License-File: LICENSE
Requires-Dist: pytest
Requires-Dist: Requests
Requires-Dist: pytest-assume
Requires-Dist: pytest-dependency
Requires-Dist: cryptography
